{"title":"前端开发调试技巧","uid":"4fa07bcbd0aa3f4d5eb9b3a018e120bd","slug":"前端开发调试技巧","date":"2022-01-19T05:42:36.000Z","updated":"2022-01-19T05:54:38.720Z","comments":true,"path":"api/articles/前端开发调试技巧.json","keywords":null,"cover":[],"content":"<h1 id=\"前端开发调试技巧\"><a href=\"#前端开发调试技巧\" class=\"headerlink\" title=\"前端开发调试技巧\"></a>前端开发调试技巧</h1><h2 id=\"前端Debug的特点\"><a href=\"#前端Debug的特点\" class=\"headerlink\" title=\"前端Debug的特点\"></a>前端Debug的特点</h2><h3 id=\"多平台\"><a href=\"#多平台\" class=\"headerlink\" title=\"多平台\"></a>多平台</h3><ul>\n<li>浏览器</li>\n<li>Hybrid</li>\n<li>NodeJs</li>\n<li>小程序</li>\n<li>桌面GUI</li>\n<li>……</li>\n</ul>\n<h3 id=\"多环境\"><a href=\"#多环境\" class=\"headerlink\" title=\"多环境\"></a>多环境</h3><ul>\n<li><p>本地开发环境</p>\n</li>\n<li><p>线上生产环境</p>\n</li>\n<li><p>…….</p>\n<span id=\"more\"></span>\n<h3 id=\"多工具\"><a href=\"#多工具\" class=\"headerlink\" title=\"多工具\"></a>多工具</h3></li>\n<li><p>Chrome Devtools</p>\n</li>\n<li><p>Charles</p>\n</li>\n<li><p>Spy-Debugger </p>\n<ul>\n<li><a href=\"https://segmentfault.com/a/1190000019462388\">spy-debugger + charles 移动端调试</a></li>\n</ul>\n</li>\n<li><p>Whistle</p>\n</li>\n<li><p>vConsole</p>\n</li>\n<li><p>……</p>\n</li>\n</ul>\n<h3 id=\"多技巧\"><a href=\"#多技巧\" class=\"headerlink\" title=\"多技巧\"></a>多技巧</h3><ul>\n<li>Console</li>\n<li>BreakPoint</li>\n<li>SourceMap</li>\n<li>代理</li>\n<li>……</li>\n</ul>\n<h2 id=\"桌面端环境-Chrome-Devtools\"><a href=\"#桌面端环境-Chrome-Devtools\" class=\"headerlink\" title=\"桌面端环境 Chrome Devtools\"></a>桌面端环境 Chrome Devtools</h2><p>一般的桌面端应用，或者开发环境下，最常用的当然是<strong>Chrome Devtools</strong>，浏览器F12或右击审查元素即可打开面板。</p>\n<p><img src=\"https://gitee.com/zeng-fanhao/figure-bed/raw/master/images/202201182327877.png\" alt=\"image-20220118232703675\"></p>\n<h3 id=\"Elements面板\"><a href=\"#Elements面板\" class=\"headerlink\" title=\"Elements面板\"></a>Elements面板</h3><p><strong>element</strong>主要用来动态地修改元素和样式，也能查看事件监听器在代码中的位置。</p>\n<ul>\n<li>点击**.cls<strong>开启动态修改元素的</strong>class**</li>\n<li>点击**:hov**查看伪类激活的效果</li>\n<li><strong>Computed</strong>下点击样式里的箭头可以跳转到<strong>Styles</strong>面板中的<strong>css</strong>规则</li>\n<li><strong>Layout</strong>可以悬停<strong>flex</strong>和<strong>grid</strong>布局的容器</li>\n<li><strong>Event Listeners</strong>查看DOM事件监听器在代码中的位置，也可以进行移除</li>\n<li><strong>Properties</strong>罗列出DOM上的所有属性</li>\n<li><strong>DOM Breakpoints</strong>快速找到修改了某一个DOM元素的Javascript代码</li>\n<li><strong>Accessibiliy</strong>跟Web无障碍相关，如<code>aria-label</code>属性</li>\n</ul>\n<h3 id=\"Console面板\"><a href=\"#Console面板\" class=\"headerlink\" title=\"Console面板\"></a>Console面板</h3><ul>\n<li><p><code>console.log</code></p>\n</li>\n<li><p><code>console.warn</code></p>\n</li>\n<li><p><code>console.error</code></p>\n</li>\n<li><p><code>console.debug</code></p>\n</li>\n<li><p><code>console.info</code></p>\n<p>面板可以选择等级，对日志进行分类：</p>\n<p><img src=\"https://gitee.com/zeng-fanhao/figure-bed/raw/master/images/202201182351731.png\" alt=\"image-20220118235111670\"></p>\n</li>\n<li><p><code>console.table</code></p>\n<p>具象化地展示<strong>JSON</strong>和<strong>数组</strong>数据</p>\n<p><img src=\"https://gitee.com/zeng-fanhao/figure-bed/raw/master/images/202201182358153.png\" alt=\"image-20220118235841097\"></p>\n</li>\n<li><p>占位符</p>\n<p>给日志添加样式，突出重要的信息，也可以通过<code>background</code>插入图片</p>\n<ul>\n<li>%s：字符串占位符</li>\n<li>%o：对象占位符</li>\n<li>%c：样式占位符</li>\n<li>%d：数字占位符</li>\n</ul>\n<p><img src=\"https://gitee.com/zeng-fanhao/figure-bed/raw/master/images/202201182357599.png\" alt=\"image-20220118235740550\"></p>\n</li>\n</ul>\n<h3 id=\"Sources面板\"><a href=\"#Sources面板\" class=\"headerlink\" title=\"Sources面板\"></a>Sources面板</h3><p>sources面板包含着项目的完整代码，提供了很多断点调试工具。</p>\n<p><img src=\"https://gitee.com/zeng-fanhao/figure-bed/raw/master/images/202201190007536.png\" alt=\"image-20220119000720467\"></p>\n<p>从左到右的区域分别是：</p>\n<ul>\n<li>页面资源文件目录</li>\n<li>代码预览区域</li>\n<li>Debug工具栏</li>\n<li>断点调试器</li>\n</ul>\n<h4 id=\"Breakpoint和Watch：\"><a href=\"#Breakpoint和Watch：\" class=\"headerlink\" title=\"Breakpoint和Watch：\"></a>Breakpoint和Watch：</h4><ol>\n<li>使用关键字<strong>debugger</strong>或代码预览区域的<strong>行号</strong>设置断点</li>\n<li>执行到断点处代码暂停执行</li>\n<li>展开<strong>Breakpoints</strong>可以看到断点列表</li>\n<li>暂停状态下，鼠标hover变量查看值</li>\n<li>在调试器Watch右侧点击 **+**可以添加对变量的监控 </li>\n</ol>\n<h4 id=\"Scope和Call-Stack：\"><a href=\"#Scope和Call-Stack：\" class=\"headerlink\" title=\"Scope和Call Stack：\"></a>Scope和Call Stack：</h4><ol>\n<li>展开<strong>Scope</strong>查看作用域列表（包含<a href=\"https://developer.mozilla.org/zh-CN/docs/Web/JavaScript/Closures\">闭包</a>）</li>\n<li>展开<strong>Call Stack</strong>可以查看当前<strong>JavaScript</strong>代码的<a href=\"https://developer.mozilla.org/zh-CN/docs/Glossary/Call_stack\">调用栈</a></li>\n</ol>\n<h4 id=\"如何调试压缩后的代码-——-SourceMap\"><a href=\"#如何调试压缩后的代码-——-SourceMap\" class=\"headerlink\" title=\"如何调试压缩后的代码 —— SourceMap\"></a>如何调试压缩后的代码 —— SourceMap</h4><p>前端代码天生具有“开源”属性，如果不经过一定的处理（<strong>压缩</strong>和<strong>变量名替换</strong>），则会有安全隐患。通常会使用<strong>Webpack</strong>之类的工具对项目的源码进行编译打包，变成类似以下的代码。</p>\n<p><img src=\"https://gitee.com/zeng-fanhao/figure-bed/raw/master/images/202201190026727.png\" alt=\"image-20220119002626586\"></p>\n<p>上面的代码不可阅读，也很难进行调试。<strong>Source Map</strong>能解决这些问题，关于它可以写多另外一篇文章进行介绍，这里先简单贴出几篇讲解sourcemap的文章，后续我也会进行详尽地学习，整理成笔记。</p>\n<blockquote><span class=\"custom-blockquote-svg\"><svg width=\"24\" height=\"24\" viewBox=\"0 0 24 24\" fill=\"\" xmlns=\"http://www.w3.org/2000/svg\" data-reactroot=\"\">\n<path fill=\"\" d=\"M22 12C22 6.5 17.5 2 12 2C6.5 2 2 6.5 2 12C2 17.5 6.5 22 12 22C13.8 22 15.5 21.5 17 20.6L22 22L20.7 17C21.5 15.5 22 13.8 22 12Z\" undefined=\"1\"></path>\n<path fill=\"\" d=\"M15.97 11.5H16.04C17.12 11.5 18 12.38 18 13.47V13.53C18 14.62 17.12 15.5 16.03 15.5H15.96C14.88 15.5 14 14.62 14 13.53V13.46C14 12.38 14.88 11.5 15.97 11.5Z\" undefined=\"1\"></path>\n<path fill=\"\" d=\"M7.97 11.5H8.04C9.12 11.5 10 12.38 10 13.47V13.53C10 14.62 9.12 15.5 8.03 15.5H7.97C6.88 15.5 6 14.62 6 13.53V13.46C6 12.38 6.88 11.5 7.97 11.5Z\" undefined=\"1\"></path>\n<path stroke-linejoin=\"round\" stroke-linecap=\"round\" stroke-miterlimit=\"10\" stroke-width=\"2\" stroke=\"\" d=\"M17 8.5C15.23 8.97 14.07 10.84 14.01 13.27C14 13.33 14 13.4 14 13.47V13.5\"></path>\n<path stroke-linejoin=\"round\" stroke-linecap=\"round\" stroke-miterlimit=\"10\" stroke-width=\"2\" stroke=\"\" d=\"M9 8.5C7.23 8.97 6.07 10.84 6.01 13.27C6 13.33 6 13.4 6 13.47V13.5\"></path>\n<path stroke-linejoin=\"round\" stroke-linecap=\"round\" stroke-miterlimit=\"10\" stroke-width=\"2\" stroke=\"\" d=\"M15.97 11.5H16.04C17.12 11.5 18 12.38 18 13.47V13.53C18 14.62 17.12 15.5 16.03 15.5H15.96C14.88 15.5 14 14.62 14 13.53V13.46C14 12.38 14.88 11.5 15.97 11.5Z\"></path>\n<path stroke-linejoin=\"round\" stroke-linecap=\"round\" stroke-miterlimit=\"10\" stroke-width=\"2\" stroke=\"\" d=\"M7.97 11.5H8.04C9.12 11.5 10 12.38 10 13.47V13.53C10 14.62 9.12 15.5 8.03 15.5H7.97C6.88 15.5 6 14.62 6 13.53V13.46C6 12.38 6.88 11.5 7.97 11.5Z\"></path>\n</svg>\n</span><ul>\n<li><p><a href=\"https://juejin.cn/post/6963076475020902436#comment\">https://juejin.cn/post/6963076475020902436#comment</a></p>\n</li>\n<li><p><a href=\"https://juejin.cn/post/6969748500938489892#comment\">https://juejin.cn/post/6969748500938489892#comment</a></p>\n</li>\n<li><p><a href=\"https://cloud.tencent.com/developer/article/1845590\">https://cloud.tencent.com/developer/article/1845590</a></p>\n</li>\n</ul></blockquote>\n<p>有了<strong>Source Map</strong>，就能在开发环境下进行调试了。当然，线上环境还是不建议开启，而是接入监控系统，如<a href=\"https://sentry.io/welcome/\">Sentry</a>，将build之后的sourcemap文件部署到内网的监控系统上。</p>\n<p><img src=\"https://gitee.com/zeng-fanhao/figure-bed/raw/master/images/202201190035627.png\" alt=\"image-20220119003510571\"></p>\n<h3 id=\"Performance面板\"><a href=\"#Performance面板\" class=\"headerlink\" title=\"Performance面板\"></a>Performance面板</h3><p><img src=\"https://gitee.com/zeng-fanhao/figure-bed/raw/master/images/202201190046620.png\" alt=\"image-20220119004626558\"></p>\n<p>从上到下依次是：</p>\n<h4 id=\"控制面板\"><a href=\"#控制面板\" class=\"headerlink\" title=\"控制面板\"></a>控制面板</h4><h4 id=\"概览面板\"><a href=\"#概览面板\" class=\"headerlink\" title=\"概览面板\"></a>概览面板</h4><ul>\n<li>FPS：每秒帧数</li>\n<li>CPU：处理各个任务花费的时间</li>\n<li>NET：各个请求花费的时间</li>\n</ul>\n<h4 id=\"线程面板\"><a href=\"#线程面板\" class=\"headerlink\" title=\"线程面板\"></a>线程面板</h4><ul>\n<li>Frames：帧线程</li>\n<li>Main：主线程，负责执行JavaScript，解析HTML/CSS，完成绘制</li>\n<li>Raster：Raster线程，负责完成某个layer或者某些块（tile）的绘制</li>\n</ul>\n<h4 id=\"统计面板\"><a href=\"#统计面板\" class=\"headerlink\" title=\"统计面板\"></a>统计面板</h4><h3 id=\"Networks面板\"><a href=\"#Networks面板\" class=\"headerlink\" title=\"Networks面板\"></a>Networks面板</h3><p>展示与网络请求相关的信息，常用于后端接口调试，以及静态资源优化等。</p>\n<p><img src=\"https://gitee.com/zeng-fanhao/figure-bed/raw/master/images/202201191256076.png\" alt=\"image-20220119125654944\"></p>\n<p>从上到下依次是：</p>\n<h4 id=\"控制面板-1\"><a href=\"#控制面板-1\" class=\"headerlink\" title=\"控制面板\"></a>控制面板</h4><h4 id=\"过滤面板\"><a href=\"#过滤面板\" class=\"headerlink\" title=\"过滤面板\"></a>过滤面板</h4><h4 id=\"概览面板-1\"><a href=\"#概览面板-1\" class=\"headerlink\" title=\"概览面板\"></a>概览面板</h4><h4 id=\"Request-Table-面板\"><a href=\"#Request-Table-面板\" class=\"headerlink\" title=\"Request Table 面板\"></a>Request Table 面板</h4><h4 id=\"总结面板\"><a href=\"#总结面板\" class=\"headerlink\" title=\"总结面板\"></a>总结面板</h4><h4 id=\"请求详情面板\"><a href=\"#请求详情面板\" class=\"headerlink\" title=\"请求详情面板\"></a>请求详情面板</h4><h3 id=\"Application面板\"><a href=\"#Application面板\" class=\"headerlink\" title=\"Application面板\"></a>Application面板</h3><p>能看到本地存储相关的信息。</p>\n<p><img src=\"https://gitee.com/zeng-fanhao/figure-bed/raw/master/images/202201191301170.png\" alt=\"image-20220119130125089\"></p>\n<h4 id=\"Local-Storage\"><a href=\"#Local-Storage\" class=\"headerlink\" title=\"Local Storage\"></a>Local Storage</h4><h4 id=\"Session-Storage\"><a href=\"#Session-Storage\" class=\"headerlink\" title=\"Session Storage\"></a>Session Storage</h4><h4 id=\"IndexedDB\"><a href=\"#IndexedDB\" class=\"headerlink\" title=\"IndexedDB\"></a>IndexedDB</h4><h4 id=\"Web-SQL\"><a href=\"#Web-SQL\" class=\"headerlink\" title=\"Web SQL\"></a>Web SQL</h4><h4 id=\"Cookie\"><a href=\"#Cookie\" class=\"headerlink\" title=\"Cookie\"></a>Cookie</h4><!--点击左侧Application下的Storage面板中的Clear Site Data可以清除网页的本地存储数据。-->\n\n\n\n<h2 id=\"移动端H5环境\"><a href=\"#移动端H5环境\" class=\"headerlink\" title=\"移动端H5环境\"></a>移动端H5环境</h2><h3 id=\"真机调试\"><a href=\"#真机调试\" class=\"headerlink\" title=\"真机调试\"></a>真机调试</h3><h4 id=\"IOS：\"><a href=\"#IOS：\" class=\"headerlink\" title=\"IOS：\"></a>IOS：</h4><ol>\n<li>使用数据线将iPhone与Mac相连</li>\n<li>iPhone开启Web检查器（设置 =&gt; Safari =&gt; 高级 =&gt; 开启Web检查器）</li>\n<li>iPhone打开要调试的页面</li>\n<li>Mac打开Safari调试（菜单栏 =&gt; 开发 =&gt; iPhone设备名 =&gt; 选择调试页面）</li>\n<li>在弹出的Safari Developer Tools中调试</li>\n</ol>\n<!--没有iPhone设备可以用Mac App Store安装Xcode使用其内置的IOS模拟器。-->\n\n<h4 id=\"Android：\"><a href=\"#Android：\" class=\"headerlink\" title=\"Android：\"></a>Android：</h4><ol>\n<li>使用数据线将手机与电脑相连</li>\n<li>手机进入开发者模式，勾选USB调试，并允许调试</li>\n<li>电脑打开Chrome，在地址栏输入：chrome://inspect/#devices并勾选Discover USB devices选项</li>\n<li>手机允许远程调试，并访问调试页面</li>\n<li>电脑点击inspect按钮</li>\n<li>进入调试页面</li>\n</ol>\n<h3 id=\"代理调试\"><a href=\"#代理调试\" class=\"headerlink\" title=\"代理调试\"></a>代理调试</h3><h4 id=\"原理\"><a href=\"#原理\" class=\"headerlink\" title=\"原理\"></a>原理</h4><ul>\n<li>电脑作为代理服务器</li>\n<li>手机通过HTTP代理连接到电脑</li>\n<li>手机上的请求都经过代理服务器</li>\n</ul>\n<h4 id=\"以Charles为例：\"><a href=\"#以Charles为例：\" class=\"headerlink\" title=\"以Charles为例：\"></a>以Charles为例：</h4><ol>\n<li>安装Charles</li>\n<li>查看电脑IP和端口</li>\n<li>将IP、端口输入手机HTTP代理</li>\n<li>Charles允许授权</li>\n<li>使用SwitchHosts软件给Mac电脑配Hosts</li>\n<li>手机访问开发环境界面</li>\n</ol>\n<!--默认情况，Charles无法抓取到HTTPS的请求，需要安装证书。-->\n\n<h4 id=\"常用工具\"><a href=\"#常用工具\" class=\"headerlink\" title=\"常用工具\"></a>常用工具</h4><ul>\n<li>Charles：适合查看、控制网络请求、分析数据</li>\n<li>Fiddler：与Charles类似，适合windows平台</li>\n<li>Spy-Debugger：远程调试手机页面、抓包</li>\n<li>Whistle：基于Node实现的跨平台Web调试代理工具</li>\n</ul>\n<h2 id=\"常用开发调试技巧\"><a href=\"#常用开发调试技巧\" class=\"headerlink\" title=\"常用开发调试技巧\"></a>常用开发调试技巧</h2><h3 id=\"线上即时修改Overrides\"><a href=\"#线上即时修改Overrides\" class=\"headerlink\" title=\"线上即时修改Overrides\"></a>线上即时修改Overrides</h3><h3 id=\"利用代理解决开发阶段的跨域问题\"><a href=\"#利用代理解决开发阶段的跨域问题\" class=\"headerlink\" title=\"利用代理解决开发阶段的跨域问题\"></a>利用代理解决开发阶段的跨域问题</h3><h3 id=\"启用本地Source-Map\"><a href=\"#启用本地Source-Map\" class=\"headerlink\" title=\"启用本地Source Map\"></a>启用本地Source Map</h3><h3 id=\"小黄鸭调试法\"><a href=\"#小黄鸭调试法\" class=\"headerlink\" title=\"小黄鸭调试法\"></a>小黄鸭调试法</h3><blockquote><span class=\"custom-blockquote-svg\"><svg width=\"24\" height=\"24\" viewBox=\"0 0 24 24\" fill=\"\" xmlns=\"http://www.w3.org/2000/svg\" data-reactroot=\"\">\n<path fill=\"\" d=\"M22 12C22 6.5 17.5 2 12 2C6.5 2 2 6.5 2 12C2 17.5 6.5 22 12 22C13.8 22 15.5 21.5 17 20.6L22 22L20.7 17C21.5 15.5 22 13.8 22 12Z\" undefined=\"1\"></path>\n<path fill=\"\" d=\"M15.97 11.5H16.04C17.12 11.5 18 12.38 18 13.47V13.53C18 14.62 17.12 15.5 16.03 15.5H15.96C14.88 15.5 14 14.62 14 13.53V13.46C14 12.38 14.88 11.5 15.97 11.5Z\" undefined=\"1\"></path>\n<path fill=\"\" d=\"M7.97 11.5H8.04C9.12 11.5 10 12.38 10 13.47V13.53C10 14.62 9.12 15.5 8.03 15.5H7.97C6.88 15.5 6 14.62 6 13.53V13.46C6 12.38 6.88 11.5 7.97 11.5Z\" undefined=\"1\"></path>\n<path stroke-linejoin=\"round\" stroke-linecap=\"round\" stroke-miterlimit=\"10\" stroke-width=\"2\" stroke=\"\" d=\"M17 8.5C15.23 8.97 14.07 10.84 14.01 13.27C14 13.33 14 13.4 14 13.47V13.5\"></path>\n<path stroke-linejoin=\"round\" stroke-linecap=\"round\" stroke-miterlimit=\"10\" stroke-width=\"2\" stroke=\"\" d=\"M9 8.5C7.23 8.97 6.07 10.84 6.01 13.27C6 13.33 6 13.4 6 13.47V13.5\"></path>\n<path stroke-linejoin=\"round\" stroke-linecap=\"round\" stroke-miterlimit=\"10\" stroke-width=\"2\" stroke=\"\" d=\"M15.97 11.5H16.04C17.12 11.5 18 12.38 18 13.47V13.53C18 14.62 17.12 15.5 16.03 15.5H15.96C14.88 15.5 14 14.62 14 13.53V13.46C14 12.38 14.88 11.5 15.97 11.5Z\"></path>\n<path stroke-linejoin=\"round\" stroke-linecap=\"round\" stroke-miterlimit=\"10\" stroke-width=\"2\" stroke=\"\" d=\"M7.97 11.5H8.04C9.12 11.5 10 12.38 10 13.47V13.53C10 14.62 9.12 15.5 8.03 15.5H7.97C6.88 15.5 6 14.62 6 13.53V13.46C6 12.38 6.88 11.5 7.97 11.5Z\"></path>\n</svg>\n</span><ul>\n<li><a href=\"https://juejin.cn/post/6844903779179954190\">急速 debug 实战二（浏览器 - 调试线上篇）</a></li>\n</ul></blockquote>\n","feature":true,"text":"前端开发调试技巧前端Debug的特点多平台 浏览器 Hybrid NodeJs 小程序 桌面GUI …… 多环境 本地开发环境 线上生产环境 ……. 多工具 Chrome Devtools Charles Spy-Debugger spy-debugger + charles 移...","link":"","photos":[],"count_time":{"symbolsCount":"2.6k","symbolsTime":"2 mins."},"categories":[],"tags":[],"toc":"<ol class=\"toc\"><li class=\"toc-item toc-level-1\"><a class=\"toc-link\" href=\"#%E5%89%8D%E7%AB%AF%E5%BC%80%E5%8F%91%E8%B0%83%E8%AF%95%E6%8A%80%E5%B7%A7\"><span class=\"toc-text\">前端开发调试技巧</span></a><ol class=\"toc-child\"><li class=\"toc-item toc-level-2\"><a class=\"toc-link\" href=\"#%E5%89%8D%E7%AB%AFDebug%E7%9A%84%E7%89%B9%E7%82%B9\"><span class=\"toc-text\">前端Debug的特点</span></a><ol class=\"toc-child\"><li class=\"toc-item toc-level-3\"><a class=\"toc-link\" href=\"#%E5%A4%9A%E5%B9%B3%E5%8F%B0\"><span class=\"toc-text\">多平台</span></a></li><li class=\"toc-item toc-level-3\"><a class=\"toc-link\" href=\"#%E5%A4%9A%E7%8E%AF%E5%A2%83\"><span class=\"toc-text\">多环境</span></a></li><li class=\"toc-item toc-level-3\"><a class=\"toc-link\" href=\"#%E5%A4%9A%E5%B7%A5%E5%85%B7\"><span class=\"toc-text\">多工具</span></a></li><li class=\"toc-item toc-level-3\"><a class=\"toc-link\" href=\"#%E5%A4%9A%E6%8A%80%E5%B7%A7\"><span class=\"toc-text\">多技巧</span></a></li></ol></li><li class=\"toc-item toc-level-2\"><a class=\"toc-link\" href=\"#%E6%A1%8C%E9%9D%A2%E7%AB%AF%E7%8E%AF%E5%A2%83-Chrome-Devtools\"><span class=\"toc-text\">桌面端环境 Chrome Devtools</span></a><ol class=\"toc-child\"><li class=\"toc-item toc-level-3\"><a class=\"toc-link\" href=\"#Elements%E9%9D%A2%E6%9D%BF\"><span class=\"toc-text\">Elements面板</span></a></li><li class=\"toc-item toc-level-3\"><a class=\"toc-link\" href=\"#Console%E9%9D%A2%E6%9D%BF\"><span class=\"toc-text\">Console面板</span></a></li><li class=\"toc-item toc-level-3\"><a class=\"toc-link\" href=\"#Sources%E9%9D%A2%E6%9D%BF\"><span class=\"toc-text\">Sources面板</span></a><ol class=\"toc-child\"><li class=\"toc-item toc-level-4\"><a class=\"toc-link\" href=\"#Breakpoint%E5%92%8CWatch%EF%BC%9A\"><span class=\"toc-text\">Breakpoint和Watch：</span></a></li><li class=\"toc-item toc-level-4\"><a class=\"toc-link\" href=\"#Scope%E5%92%8CCall-Stack%EF%BC%9A\"><span class=\"toc-text\">Scope和Call Stack：</span></a></li><li class=\"toc-item toc-level-4\"><a class=\"toc-link\" href=\"#%E5%A6%82%E4%BD%95%E8%B0%83%E8%AF%95%E5%8E%8B%E7%BC%A9%E5%90%8E%E7%9A%84%E4%BB%A3%E7%A0%81-%E2%80%94%E2%80%94-SourceMap\"><span class=\"toc-text\">如何调试压缩后的代码 —— SourceMap</span></a></li></ol></li><li class=\"toc-item toc-level-3\"><a class=\"toc-link\" href=\"#Performance%E9%9D%A2%E6%9D%BF\"><span class=\"toc-text\">Performance面板</span></a><ol class=\"toc-child\"><li class=\"toc-item toc-level-4\"><a class=\"toc-link\" href=\"#%E6%8E%A7%E5%88%B6%E9%9D%A2%E6%9D%BF\"><span class=\"toc-text\">控制面板</span></a></li><li class=\"toc-item toc-level-4\"><a class=\"toc-link\" href=\"#%E6%A6%82%E8%A7%88%E9%9D%A2%E6%9D%BF\"><span class=\"toc-text\">概览面板</span></a></li><li class=\"toc-item toc-level-4\"><a class=\"toc-link\" href=\"#%E7%BA%BF%E7%A8%8B%E9%9D%A2%E6%9D%BF\"><span class=\"toc-text\">线程面板</span></a></li><li class=\"toc-item toc-level-4\"><a class=\"toc-link\" href=\"#%E7%BB%9F%E8%AE%A1%E9%9D%A2%E6%9D%BF\"><span class=\"toc-text\">统计面板</span></a></li></ol></li><li class=\"toc-item toc-level-3\"><a class=\"toc-link\" href=\"#Networks%E9%9D%A2%E6%9D%BF\"><span class=\"toc-text\">Networks面板</span></a><ol class=\"toc-child\"><li class=\"toc-item toc-level-4\"><a class=\"toc-link\" href=\"#%E6%8E%A7%E5%88%B6%E9%9D%A2%E6%9D%BF-1\"><span class=\"toc-text\">控制面板</span></a></li><li class=\"toc-item toc-level-4\"><a class=\"toc-link\" href=\"#%E8%BF%87%E6%BB%A4%E9%9D%A2%E6%9D%BF\"><span class=\"toc-text\">过滤面板</span></a></li><li class=\"toc-item toc-level-4\"><a class=\"toc-link\" href=\"#%E6%A6%82%E8%A7%88%E9%9D%A2%E6%9D%BF-1\"><span class=\"toc-text\">概览面板</span></a></li><li class=\"toc-item toc-level-4\"><a class=\"toc-link\" href=\"#Request-Table-%E9%9D%A2%E6%9D%BF\"><span class=\"toc-text\">Request Table 面板</span></a></li><li class=\"toc-item toc-level-4\"><a class=\"toc-link\" href=\"#%E6%80%BB%E7%BB%93%E9%9D%A2%E6%9D%BF\"><span class=\"toc-text\">总结面板</span></a></li><li class=\"toc-item toc-level-4\"><a class=\"toc-link\" href=\"#%E8%AF%B7%E6%B1%82%E8%AF%A6%E6%83%85%E9%9D%A2%E6%9D%BF\"><span class=\"toc-text\">请求详情面板</span></a></li></ol></li><li class=\"toc-item toc-level-3\"><a class=\"toc-link\" href=\"#Application%E9%9D%A2%E6%9D%BF\"><span class=\"toc-text\">Application面板</span></a><ol class=\"toc-child\"><li class=\"toc-item toc-level-4\"><a class=\"toc-link\" href=\"#Local-Storage\"><span class=\"toc-text\">Local Storage</span></a></li><li class=\"toc-item toc-level-4\"><a class=\"toc-link\" href=\"#Session-Storage\"><span class=\"toc-text\">Session Storage</span></a></li><li class=\"toc-item toc-level-4\"><a class=\"toc-link\" href=\"#IndexedDB\"><span class=\"toc-text\">IndexedDB</span></a></li><li class=\"toc-item toc-level-4\"><a class=\"toc-link\" href=\"#Web-SQL\"><span class=\"toc-text\">Web SQL</span></a></li><li class=\"toc-item toc-level-4\"><a class=\"toc-link\" href=\"#Cookie\"><span class=\"toc-text\">Cookie</span></a></li></ol></li></ol></li><li class=\"toc-item toc-level-2\"><a class=\"toc-link\" href=\"#%E7%A7%BB%E5%8A%A8%E7%AB%AFH5%E7%8E%AF%E5%A2%83\"><span class=\"toc-text\">移动端H5环境</span></a><ol class=\"toc-child\"><li class=\"toc-item toc-level-3\"><a class=\"toc-link\" href=\"#%E7%9C%9F%E6%9C%BA%E8%B0%83%E8%AF%95\"><span class=\"toc-text\">真机调试</span></a><ol class=\"toc-child\"><li class=\"toc-item toc-level-4\"><a class=\"toc-link\" href=\"#IOS%EF%BC%9A\"><span class=\"toc-text\">IOS：</span></a></li><li class=\"toc-item toc-level-4\"><a class=\"toc-link\" href=\"#Android%EF%BC%9A\"><span class=\"toc-text\">Android：</span></a></li></ol></li><li class=\"toc-item toc-level-3\"><a class=\"toc-link\" href=\"#%E4%BB%A3%E7%90%86%E8%B0%83%E8%AF%95\"><span class=\"toc-text\">代理调试</span></a><ol class=\"toc-child\"><li class=\"toc-item toc-level-4\"><a class=\"toc-link\" href=\"#%E5%8E%9F%E7%90%86\"><span class=\"toc-text\">原理</span></a></li><li class=\"toc-item toc-level-4\"><a class=\"toc-link\" href=\"#%E4%BB%A5Charles%E4%B8%BA%E4%BE%8B%EF%BC%9A\"><span class=\"toc-text\">以Charles为例：</span></a></li><li class=\"toc-item toc-level-4\"><a class=\"toc-link\" href=\"#%E5%B8%B8%E7%94%A8%E5%B7%A5%E5%85%B7\"><span class=\"toc-text\">常用工具</span></a></li></ol></li></ol></li><li class=\"toc-item toc-level-2\"><a class=\"toc-link\" href=\"#%E5%B8%B8%E7%94%A8%E5%BC%80%E5%8F%91%E8%B0%83%E8%AF%95%E6%8A%80%E5%B7%A7\"><span class=\"toc-text\">常用开发调试技巧</span></a><ol class=\"toc-child\"><li class=\"toc-item toc-level-3\"><a class=\"toc-link\" href=\"#%E7%BA%BF%E4%B8%8A%E5%8D%B3%E6%97%B6%E4%BF%AE%E6%94%B9Overrides\"><span class=\"toc-text\">线上即时修改Overrides</span></a></li><li class=\"toc-item toc-level-3\"><a class=\"toc-link\" href=\"#%E5%88%A9%E7%94%A8%E4%BB%A3%E7%90%86%E8%A7%A3%E5%86%B3%E5%BC%80%E5%8F%91%E9%98%B6%E6%AE%B5%E7%9A%84%E8%B7%A8%E5%9F%9F%E9%97%AE%E9%A2%98\"><span class=\"toc-text\">利用代理解决开发阶段的跨域问题</span></a></li><li class=\"toc-item toc-level-3\"><a class=\"toc-link\" href=\"#%E5%90%AF%E7%94%A8%E6%9C%AC%E5%9C%B0Source-Map\"><span class=\"toc-text\">启用本地Source Map</span></a></li><li class=\"toc-item toc-level-3\"><a class=\"toc-link\" href=\"#%E5%B0%8F%E9%BB%84%E9%B8%AD%E8%B0%83%E8%AF%95%E6%B3%95\"><span class=\"toc-text\">小黄鸭调试法</span></a></li></ol></li></ol></li></ol>","author":{"name":"EVE","slug":"blog-author","avatar":"https://gitee.com/zeng-fanhao/figure-bed/raw/master/images/202201171207395.png","link":"/","description":"keep calm, own minds </br>  put thoughts forward","socials":{"github":"https://github.com/starryeve","twitter":"","stackoverflow":"","wechat":"","qq":"","weibo":"","zhihu":"","csdn":"","juejin":"https://juejin.cn/user/562570281888488","customs":{}}},"mapped":true,"prev_post":{"title":"如何写好JavaScript代码","uid":"66d5432935a9e114e0c6473f5ec12a37","slug":"如何写好JavaScript代码","date":"2022-01-19T15:20:00.000Z","updated":"2022-01-19T15:22:56.620Z","comments":true,"path":"api/articles/如何写好JavaScript代码.json","keywords":null,"cover":[],"text":"写好JS的三个原则各司其职Web天然具有分层的体系架构，HTML、CSS、JavaScript各自承担着结构、表现和行为的责任，这种鲜明的三层结构就能在一定程度上指导我们设计一个高可用、高可扩展的应用。 网页换肤以一个具备 白天/夜间 模式切换的页面为例，我们先给出基本的HTML...","link":"","photos":[],"count_time":{"symbolsCount":"9.3k","symbolsTime":"8 mins."},"categories":[],"tags":[],"author":{"name":"EVE","slug":"blog-author","avatar":"https://gitee.com/zeng-fanhao/figure-bed/raw/master/images/202201171207395.png","link":"/","description":"keep calm, own minds </br>  put thoughts forward","socials":{"github":"https://github.com/starryeve","twitter":"","stackoverflow":"","wechat":"","qq":"","weibo":"","zhihu":"","csdn":"","juejin":"https://juejin.cn/user/562570281888488","customs":{}}},"feature":true},"next_post":{"title":"win向mac环境迁移","uid":"efa091f902e958fe5c4762b87ffa7084","slug":"win向mac环境迁移","date":"2021-10-02T16:22:33.000Z","updated":"2022-01-18T17:16:01.127Z","comments":true,"path":"api/articles/win向mac环境迁移.json","keywords":null,"cover":"https://gitee.com/zeng-fanhao/figure-bed/raw/master/images/202201190115927.jpg","text":"win 切换到 mac 的环境迁移买不起 mac，在同学的怂恿下装了黑 mac，前前后后折腾了两三天，总算稳定下来，能开始干活了。 mac 的开发体验确实很舒服，类 linux 的 shell 命令，各种好用的安装工具、终端工具等等。这篇文章主要是记录一下从 win 过渡到 ma...","link":"","photos":[],"count_time":{"symbolsCount":"9.7k","symbolsTime":"9 mins."},"categories":[],"tags":[],"author":{"name":"EVE","slug":"blog-author","avatar":"https://gitee.com/zeng-fanhao/figure-bed/raw/master/images/202201171207395.png","link":"/","description":"keep calm, own minds </br>  put thoughts forward","socials":{"github":"https://github.com/starryeve","twitter":"","stackoverflow":"","wechat":"","qq":"","weibo":"","zhihu":"","csdn":"","juejin":"https://juejin.cn/user/562570281888488","customs":{}}}}}